datu/__init__.py
datu/app_config.py
datu/main.py
datu/py.typed
datu/base/__init__.py
datu/base/base_connector.py
datu/base/chat_schema.py
datu/base/llm_client.py
datu/factory/__init__.py
datu/factory/db_connector.py
datu/factory/llm_client_factory.py
datu/integrations/__init__.py
datu/integrations/config.py
datu/integrations/dbt/__init__.py
datu/integrations/dbt/config.py
datu/integrations/postgre_sql/__init__.py
datu/integrations/postgre_sql/postgre_connector.py
datu/integrations/sql_server/__init__.py
datu/integrations/sql_server/sqldb_connector.py
datu/llm_clients/__init__.py
datu/llm_clients/openai_client.py
datu/mcp/__init__.py
datu/mcp/config.py
datu/mcp/tools/sql_generator.py
datu/routers/__init__.py
datu/routers/chat.py
datu/routers/data_sources.py
datu/routers/llm_context.py
datu/routers/metadata.py
datu/routers/transformations.py
datu/schema_extractor/__init__.py
datu/schema_extractor/schema_cache.py
datu/server/__init__.py
datu/server/build/asset-manifest.json
datu/server/build/favicon.ico
datu/server/build/index.html
datu/server/build/static/css/main.8ea602e6.css
datu/server/build/static/css/main.8ea602e6.css.map
datu/server/build/static/js/main.492ce101.js
datu/server/build/static/js/main.492ce101.js.LICENSE.txt
datu/server/build/static/js/main.492ce101.js.map
datu/server/build/static/js/main.5f05d010.js
datu/server/build/static/js/main.5f05d010.js.LICENSE.txt
datu/server/build/static/js/main.5f05d010.js.map
datu/server/build/static/media/codicon.b797181c93b3755f4fa1.ttf
datu/services/__init__.py
datu/services/config.py
datu/services/llm.py
datu/services/schema_rag.py
datu/services/sql_generator/core.py
datu/services/sql_generator/normalizer.py
datu/telemetry/__init__.py
datu/telemetry/config.py
datu/telemetry/product/__init__.py
datu/telemetry/product/events.py
datu/telemetry/product/posthog.py
datu_core-0.0.3.dist-info/METADATA
datu_core-0.0.3.dist-info/WHEEL
datu_core-0.0.3.dist-info/entry_points.txt
datu_core-0.0.3.dist-info/licenses/LICENSE
datu_core-0.0.3.dist-info/RECORD
