Metadata-Version: 2.4
Name: datu-core
Version: 0.0.3
Summary: LLM-Driven Data Transformations
Project-URL: Homepage, https://datu.fi
Project-URL: Bug Tracker, https://github.com/Datuanalytics/datu-core/issues
Project-URL: Documentation, https://docs.datu.fi
Author-email: Datu <hello@datu.fi>
Maintainer-email: Datu <hello@datu.fi>
License: Apache-2.0
License-File: LICENSE
Classifier: Programming Language :: Python :: 3 :: Only
Classifier: Programming Language :: Python :: 3.11
Classifier: Programming Language :: Python :: 3.12
Classifier: Topic :: Software Development :: Libraries :: Python Modules
Requires-Python: <3.13,>=3.11
Requires-Dist: fastapi>=0.115.11
Requires-Dist: fastmcp>=2.10.5
Requires-Dist: langchain-community<0.4,>=0.3
Requires-Dist: langchain-core>=0.1.41
Requires-Dist: langchain-mcp-adapters>=0.1.8
Requires-Dist: langchain-openai<0.4,>=0.3
Requires-Dist: langchain>=0.3
Requires-Dist: langgraph>=0.0.37
Requires-Dist: mcp-use[search]>=1.3.7
Requires-Dist: networkx>=3.0
Requires-Dist: numpy<2.0.0
Requires-Dist: onnxruntime==1.19.2; sys_platform == 'darwin' and platform_machine == 'x86_64'
Requires-Dist: openai>=1.30.1
Requires-Dist: posthog>=6.5.0
Requires-Dist: pydantic-settings>=2.8.1
Requires-Dist: safetensors<0.7,>=0.6.2
Requires-Dist: sentence-transformers>=2.5.1
Requires-Dist: sql-metadata>=2.17.0
Requires-Dist: torch==2.2.2
Requires-Dist: transformers<4.44.0
Requires-Dist: types-psycopg2>=2.9.21.20250318
Requires-Dist: types-pyyaml>=6.0.12.20250402
Requires-Dist: uvicorn>=0.22.0
Provides-Extra: all
Requires-Dist: psycopg2-binary>=2.9.6; extra == 'all'
Requires-Dist: pyodbc>=5.2.0; extra == 'all'
Provides-Extra: dev
Requires-Dist: bandit>=1.8.3; extra == 'dev'
Requires-Dist: hatch-vcs<1.0.0,>=0.3.0; extra == 'dev'
Requires-Dist: hatch<2.0.0,>=1.0.0; extra == 'dev'
Requires-Dist: httpx; extra == 'dev'
Requires-Dist: mypy; extra == 'dev'
Requires-Dist: pre-commit>=4.2.0; extra == 'dev'
Requires-Dist: pylint>=3.3.6; extra == 'dev'
Requires-Dist: pytest; extra == 'dev'
Requires-Dist: pytest-asyncio>=0.23.0; extra == 'dev'
Requires-Dist: pytest-cov; extra == 'dev'
Requires-Dist: responses>=0.25.7; extra == 'dev'
Requires-Dist: ruff; extra == 'dev'
Requires-Dist: toml>=0.10.2; extra == 'dev'
Requires-Dist: tomlkit>=0.13.2; extra == 'dev'
Requires-Dist: towncrier>=24.8.0; extra == 'dev'
Requires-Dist: tox; extra == 'dev'
Requires-Dist: types-networkx>=3.5.0; extra == 'dev'
Requires-Dist: types-toml>=0.10.8.20240310; extra == 'dev'
Provides-Extra: docs
Requires-Dist: mkdocs-macros-plugin~=1.3.7; extra == 'docs'
Requires-Dist: mkdocs-material~=9.6.12; extra == 'docs'
Requires-Dist: mkdocstrings-python~=1.16.10; extra == 'docs'
Requires-Dist: mkdocs~=1.6.1; extra == 'docs'
Requires-Dist: sphinx-autodoc-typehints<2.0.0,>=1.12.0; extra == 'docs'
Requires-Dist: sphinx-rtd-theme<2.0.0,>=1.0.0; extra == 'docs'
Requires-Dist: sphinx<6.0.0,>=5.0.0; extra == 'docs'
Provides-Extra: postgres
Requires-Dist: psycopg2-binary>=2.9.6; extra == 'postgres'
Provides-Extra: sqldb
Requires-Dist: pyodbc>=5.2.0; extra == 'sqldb'
